logistigate/__init__.py
logistigate/lg.py
logistigate/methods.py
logistigate/utilities.py
logistigate/data/example1TestData.csv
logistigate/data/example1TransitionMatrix.csv
logistigate/data/example1TrueRates.csv
logistigate/data/example1bTestData.csv
logistigate/data/example1cTestData.csv
logistigate/data/example2TestData.csv
logistigate/data/example2TransitionMatrix.csv
logistigate/data/example2TrueRates.csv
logistigate-0.1.0.dist-info/LICENSE.txt
logistigate-0.1.0.dist-info/METADATA
logistigate-0.1.0.dist-info/WHEEL
logistigate-0.1.0.dist-info/top_level.txt
logistigate-0.1.0.dist-info/RECORD
