Metadata-Version: 2.1
Name: logistigate
Version: 0.1.0
Summary: python implementation of logistigate for supply-chain aberration inference
Home-page: https://github.com/eugenewickett/logistigate
Author: Eugene Wickett, Karen Smilowitz, Matthew Plumlee
Author-email: eugenewickett@u.northwestern.edu
License: UNKNOWN
Keywords: supply chains,statistical inference,pharmaceutical regulation
Platform: UNKNOWN
Classifier: Development Status :: 3 - Alpha
Classifier: Intended Audience :: Science/Research
Classifier: Topic :: Scientific/Engineering :: Medical Science Apps.
Classifier: License :: OSI Approved :: MIT License
Classifier: Programming Language :: Python :: 3
Requires-Python: >=3
Requires-Dist: nuts
Requires-Dist: numpy
Requires-Dist: tabulate
Requires-Dist: scipy
Requires-Dist: matplotlib
